setup.py
distributions_elnurvl/Binomialdistribution.py
distributions_elnurvl/Gaussiandistribution.py
distributions_elnurvl/Generaldistribution.py
distributions_elnurvl/__init__.py
distributions_elnurvl.egg-info/PKG-INFO
distributions_elnurvl.egg-info/SOURCES.txt
distributions_elnurvl.egg-info/dependency_links.txt
distributions_elnurvl.egg-info/not-zip-safe
distributions_elnurvl.egg-info/top_level.txt