Metadata-Version: 1.0
Name: distributions-elnurvl
Version: 0.1
Summary: Gaussian and Binomial distributions
Home-page: UNKNOWN
Author: Elnur Hajiyev
Author-email: elnurvl@gmail.com
License: UNKNOWN
Platform: UNKNOWN
